jvc_projector/__init__.py
jvc_projector/commands.py
jvc_projector/errors.py
jvc_projector/jvc_projector.py
tests/__init__.py
tests/testLowLatency.py
pyjvc-5.0.1.dist-info/LICENSE
pyjvc-5.0.1.dist-info/METADATA
pyjvc-5.0.1.dist-info/WHEEL
pyjvc-5.0.1.dist-info/top_level.txt
pyjvc-5.0.1.dist-info/RECORD
